holopy/__init__.py
holopy-0.1.0.dist-info/METADATA
holopy-0.1.0.dist-info/WHEEL
holopy-0.1.0.dist-info/top_level.txt
holopy-0.1.0.dist-info/RECORD
